rsArtdReformatter/__init__.py
rsArtdReformatter/reformat.py
rsArtdReformatter-1.0.3.dist-info/LICENCE
rsArtdReformatter-1.0.3.dist-info/METADATA
rsArtdReformatter-1.0.3.dist-info/WHEEL
rsArtdReformatter-1.0.3.dist-info/entry_points.txt
rsArtdReformatter-1.0.3.dist-info/top_level.txt
rsArtdReformatter-1.0.3.dist-info/RECORD
