Metadata-Version: 2.1
Name: rsArtdReformatter
Version: 1.0.3
Summary: A tool to reformat the output of the ARtD tool
Author-email: Frankie Hadwick <frankie@ramseysystems.co.uk>, Charlie McCay <charlie@ramseysystems.co.uk>
Project-URL: Homepage, https://github.com/FrankiePH/rsArtdReformatter.git
Keywords: reformatter,artd,artd-reformatter,rsArtdReformatter
Classifier: License :: OSI Approved :: MIT License
Classifier: Programming Language :: Python :: 3
Classifier: Programming Language :: Python :: 3.6
Requires-Python: >=3.6
License-File: LICENCE
Provides-Extra: dev
Requires-Dist: pytest ; extra == 'dev'
Requires-Dist: pytest-cov ; extra == 'dev'
Requires-Dist: flake8 ; extra == 'dev'
Requires-Dist: black ; extra == 'dev'
Requires-Dist: isort ; extra == 'dev'
